ntracer/__init__.py
ntracer/libgcc_s_seh-1.dll
ntracer/libstdc++-6.dll
ntracer/libwinpthread-1.dll
ntracer/pygame_render.py
ntracer/render.cp39-win_amd64.pyd
ntracer/tracer3.cp39-win_amd64.pyd
ntracer/tracer4.cp39-win_amd64.pyd
ntracer/tracer5.cp39-win_amd64.pyd
ntracer/tracer6.cp39-win_amd64.pyd
ntracer/tracer7.cp39-win_amd64.pyd
ntracer/tracer8.cp39-win_amd64.pyd
ntracer/tracern.cp39-win_amd64.pyd
ntracer/wavefront_obj.py
ntracer/wrapper.py
ntracer/tests/__init__.py
ntracer/tests/test.py
ntracer-0.10.3.data/scripts/hypercube.py
ntracer-0.10.3.data/scripts/polytope.py
ntracer-0.10.3.dist-info/LICENSE.txt
ntracer-0.10.3.dist-info/METADATA
ntracer-0.10.3.dist-info/WHEEL
ntracer-0.10.3.dist-info/top_level.txt
ntracer-0.10.3.dist-info/zip-safe
ntracer-0.10.3.dist-info/RECORD
